family_ai_voice_assistant/__init__.py
family_ai_voice_assistant/tools/__init__.py
family_ai_voice_assistant/tools/configs/__init__.py
family_ai_voice_assistant/tools/configs/bulitin_tools_config.py
family_ai_voice_assistant/tools/functions/__init__.py
family_ai_voice_assistant/tools/functions/combination_tools.py
family_ai_voice_assistant/tools/functions/core.py
family_ai_voice_assistant/tools/functions/executors.py
family_ai_voice_assistant/tools/functions/local_apis.py
family_ai_voice_assistant/tools/functions/search.py
family_ai_voice_assistant/tools/functions/web_apis.py
family_ai_voice_assistant/tools/resources/constants_chs.json
family_ai_voice_assistant/tools/resources/constants_en.json
family_ai_voice_assistant_tools-0.1.0.dist-info/METADATA
family_ai_voice_assistant_tools-0.1.0.dist-info/WHEEL
family_ai_voice_assistant_tools-0.1.0.dist-info/RECORD
