Metadata-Version: 2.1
Name: family-ai-voice-assistant-tools
Version: 0.1.0
Summary: Built-in tools for the Family AI Voice Assistant.
Home-page: https://github.com/augaria/family-ai-voice-assistant/tree/augaria/dev/src/family-ai-voice-assistant-tools
License: MIT
Author: Augaria
Author-email: augaria@163.com
Requires-Python: >=3.9,<4.0
Classifier: License :: OSI Approved :: MIT License
Classifier: Programming Language :: Python :: 3
Classifier: Programming Language :: Python :: 3.9
Classifier: Programming Language :: Python :: 3.10
Classifier: Programming Language :: Python :: 3.11
Classifier: Programming Language :: Python :: 3.12
Classifier: Programming Language :: Python :: 3.13
Requires-Dist: apscheduler
Requires-Dist: bs4
Requires-Dist: family-ai-voice-assistant-core
Requires-Dist: google-search-results
Requires-Dist: pymongo
Project-URL: Repository, https://github.com/augaria/family-ai-voice-assistant/tree/augaria/dev/src/family-ai-voice-assistant-tools
